MANIFEST.in
README.md
requirements.txt
setup.cfg
setup.py
./aws360api/__init__.py
./aws360api/config/__init__.py
./aws360api/config/config.py
./aws360api/heartbeat/__init__.py
./aws360api/heartbeat/controllers.py
./aws360api/info/__init__.py
./aws360api/info/controllers.py
aws360api/__init__.py
aws360api.egg-info/PKG-INFO
aws360api.egg-info/SOURCES.txt
aws360api.egg-info/dependency_links.txt
aws360api.egg-info/not-zip-safe
aws360api.egg-info/requires.txt
aws360api.egg-info/top_level.txt
aws360api/config/__init__.py
aws360api/config/config.py
aws360api/heartbeat/__init__.py
aws360api/heartbeat/controllers.py
aws360api/info/__init__.py
aws360api/info/controllers.py
aws360api/iot/__init__.py
aws360api/iot/controllers.py
aws360api/templates/badge.html