Metadata-Version: 1.0
Name: aws360api
Version: 0.0.10
Summary: Flask API used in AWS-360 courses
Home-page: UNKNOWN
Author: Florian Dambrine
Author-email: android.florian@gmail.com
License: BSD
Keywords: aws-360,flask
Platform: UNKNOWN
